csv_project/__init__.py
csv_file-1.0.dist-info/METADATA
csv_file-1.0.dist-info/WHEEL
csv_file-1.0.dist-info/top_level.txt
csv_file-1.0.dist-info/RECORD
