Metadata-Version: 2.1
Name: csv_file
Version: 1.0
Summary: This repository which was created to facilitate working with csv
Home-page: https://github.com/Bernax27/myrepository1/tree/main
Author: Bernax27
Author-email: Roman-16016@yandex.ru
License: UNKNOWN
Platform: UNKNOWN
Classifier: Programming Language :: Python :: 3
Classifier: License :: OSI Approved :: MIT License
Classifier: Operating System :: OS Independent
Requires-Python: >=3.6
